netstorageapi-1.2.12-py3.6-nspkg.pth
akamai/netstorage/__init__.py
akamai/netstorage/netstorage.py
netstorageapi-1.2.12.dist-info/DESCRIPTION.rst
netstorageapi-1.2.12.dist-info/METADATA
netstorageapi-1.2.12.dist-info/RECORD
netstorageapi-1.2.12.dist-info/WHEEL
netstorageapi-1.2.12.dist-info/metadata.json
netstorageapi-1.2.12.dist-info/namespace_packages.txt
netstorageapi-1.2.12.dist-info/top_level.txt
netstorageapi-1.2.12.dist-info/backup/netstorageapi-1.2.10-py2.py3-none-any.whl
netstorageapi-1.2.12.dist-info/backup/netstorageapi-1.2.10.tar.gz
netstorageapi-1.2.12.dist-info/backup/netstorageapi-1.2.10.zip
netstorageapi-1.2.12.dist-info/backup/netstorageapi-1.2.8-py2.py3-none-any.whl
netstorageapi-1.2.12.dist-info/backup/netstorageapi-1.2.8.tar.gz
netstorageapi-1.2.12.dist-info/backup/netstorageapi-1.2.8.zip
netstorageapi-1.2.12.dist-info/backup/netstorageapi-1.2.9-py2.py3-none-any.whl
netstorageapi-1.2.12.dist-info/backup/netstorageapi-1.2.9.tar.gz
netstorageapi-1.2.12.dist-info/backup/netstorageapi-1.2.9.zip
