Metadata-Version: 2.0
Name: netstorageapi
Version: 1.2.12
Summary: Akamai Netstorage API for Python
Home-page: https://github.com/AstinCHOI/akamai-netstorage
Author: Astin Choi
Author-email: asciineo@gmail.com
License: Apache 2.0
Keywords: netstorage akamai open api
Platform: UNKNOWN
Classifier: Intended Audience :: Developers
Classifier: Programming Language :: Python
Classifier: Programming Language :: Python :: 2.6
Classifier: Programming Language :: Python :: 2.7
Classifier: Programming Language :: Python :: 3
Classifier: Programming Language :: Python :: 3.3
Classifier: Programming Language :: Python :: 3.4
Classifier: Programming Language :: Python :: 3.5
Classifier: Programming Language :: Python :: 3.6
Classifier: Programming Language :: Python :: Implementation :: CPython
Classifier: Programming Language :: Python :: Implementation :: PyPy
Requires-Dist: requests
